simple_wer/__init__.py
simple_wer/simple_wer.py
simple_wer/simple_wer_cli.py
simple_wer-0.2.dist-info/LICENSE
simple_wer-0.2.dist-info/METADATA
simple_wer-0.2.dist-info/WHEEL
simple_wer-0.2.dist-info/entry_points.txt
simple_wer-0.2.dist-info/top_level.txt
simple_wer-0.2.dist-info/RECORD
