Metadata-Version: 2.1
Name: simple-wer
Version: 0.2
Summary: A simple commandline tool for calculating WERs.
Author-email: Wei Kang <wkang.pku@gmail.com>
Project-URL: Homepage, https://github.com/pkufool/simple-wer
Project-URL: Bug Tracker, https://github.com/pkufool/simple-wer/issues
Classifier: Programming Language :: Python :: 3
Classifier: License :: OSI Approved :: Apache Software License
Classifier: Operating System :: OS Independent
Requires-Python: >=3.7
License-File: LICENSE
Requires-Dist: click (>=6.7)
Requires-Dist: kaldialign
